FoxDotM/__init__.py
foxdotm-0.1.0.post0.dist-info/METADATA
foxdotm-0.1.0.post0.dist-info/WHEEL
foxdotm-0.1.0.post0.dist-info/licenses/LICENSE
foxdotm-0.1.0.post0.dist-info/RECORD
